bls_py/tests.py
bls_py/ec.py
bls_py/fields_t.py
bls_py/tdata.py
bls_py/util.py
bls_py/aggregation_info.py
bls_py/bls12381.py
bls_py/fields_t_c.cpython-36m-x86_64-linux-gnu.so
bls_py/__init__.py
bls_py/keys.py
bls_py/fields.py
bls_py/signature.py
bls_py/pairing.py
bls_py/threshold.py
bls_py/bls.py
python_bls-0.1.10.dist-info/WHEEL
python_bls-0.1.10.dist-info/RECORD
python_bls-0.1.10.dist-info/METADATA
python_bls-0.1.10.dist-info/LICENSE
python_bls-0.1.10.dist-info/top_level.txt
python_bls.libs/libgmp-8cad5d65.so.10.4.1
