Metadata-Version: 2.1
Name: python-bls
Version: 0.1.10
Summary: BLS12-381 and Signatures in python
Home-page: https://github.com/zebra-lucky/python-bls
License: Apache License 2.0
Platform: any
Requires-Python: >=3.6
